mcp_server_funcat/__init__.py
mcp_server_funcat/__main__.py
mcp_server_funcat/cat.py
mcp_server_funcat/server.py
mcp_server_funcat-0.2.3.dist-info/WHEEL
mcp_server_funcat-0.2.3.dist-info/entry_points.txt
mcp_server_funcat-0.2.3.dist-info/METADATA
mcp_server_funcat-0.2.3.dist-info/RECORD
