Metadata-Version: 2.3
Name: mcp-server-funcat
Version: 0.2.3
Summary: MCP Server for Funcat
Author: lukbai
Author-email: lukbai <baibaibai_000@gmail.com>
Requires-Dist: fastmcp>=2.10.0
Requires-Dist: requests
Requires-Python: >=3.10
